AUTHORS.rst
CONTRIBUTING.rst
HISTORY.rst
LICENSE
MANIFEST.in
README.rst
setup.cfg
setup.py
MPPyResponse/MPPyResponse.py
MPPyResponse/__init__.py
MPPyResponse/monty_python.txt
MPPyResponse.egg-info/PKG-INFO
MPPyResponse.egg-info/SOURCES.txt
MPPyResponse.egg-info/dependency_links.txt
MPPyResponse.egg-info/entry_points.txt
MPPyResponse.egg-info/not-zip-safe
MPPyResponse.egg-info/top_level.txt
docs/Makefile
docs/authors.rst
docs/conf.py
docs/contributing.rst
docs/history.rst
docs/index.rst
docs/installation.rst
docs/make.bat
docs/readme.rst
docs/usage.rst
tests/__init__.py
tests/test_Monty-Python-PyResponse.py