Metadata-Version: 1.1
Name: MPPyResponse
Version: 0.1.3
Summary: A silly Monty Python quote generator
Home-page: https://github.com/drincruz/Monty-Python-PyResponse
Author: Adrian Cruz
Author-email: drincruz@gmail.com
License: MIT
Keywords: MPPyResponse
Platform: UNKNOWN
Classifier: Development Status :: 2 - Pre-Alpha
Classifier: Intended Audience :: Developers
Classifier: License :: OSI Approved :: MIT License
Classifier: Natural Language :: English
Classifier: Programming Language :: Python :: 2
Classifier: Programming Language :: Python :: 2.6
Classifier: Programming Language :: Python :: 2.7
Classifier: Programming Language :: Python :: 3
Classifier: Programming Language :: Python :: 3.3
Classifier: Programming Language :: Python :: 3.4
